RegressionVisualizer3D/__init__.py
RegressionVisualizer3D/visualizer.py
RegressionVisualizer3D-1.2.4.dist-info/LICENSE.txt
RegressionVisualizer3D-1.2.4.dist-info/METADATA
RegressionVisualizer3D-1.2.4.dist-info/WHEEL
RegressionVisualizer3D-1.2.4.dist-info/top_level.txt
RegressionVisualizer3D-1.2.4.dist-info/RECORD
