Metadata-Version: 2.1
Name: RegressionVisualizer3D
Version: 1.2.4
Summary: This is a simple plotting package for visualizing linear regression, Poisson regression and binary logistic regression in 3D, for teaching purposes.
Home-page: https://github.com/pxr687/RegressionVisualizer3D
Author: pxr687
License: UNKNOWN
Keywords: regression,linear regression,poisson regression,logistic regression,visualization,3D,visualisation
Platform: UNKNOWN
Requires-Python: >=3.7
License-File: LICENSE.txt
